mcp_weahter_sse/__init__.py
mcp_weahter_sse/main.py
mcp_weahter_sse/server.py
mcp_weahter_sse-0.1.0.dist-info/METADATA
mcp_weahter_sse-0.1.0.dist-info/WHEEL
mcp_weahter_sse-0.1.0.dist-info/entry_points.txt
mcp_weahter_sse-0.1.0.dist-info/top_level.txt
mcp_weahter_sse-0.1.0.dist-info/RECORD
